llms/__init__.py
llms/llms.py
llms/providers/__init__.py
llms/providers/ai21.py
llms/providers/aleph.py
llms/providers/anthropic.py
llms/providers/base_provider.py
llms/providers/bedrock_anthropic.py
llms/providers/cohere.py
llms/providers/deepseek.py
llms/providers/google_genai.py
llms/providers/groq.py
llms/providers/huggingface.py
llms/providers/llms.py
llms/providers/mistral.py
llms/providers/ollama.py
llms/providers/openai.py
llms/providers/openrouter.py
llms/providers/reka.py
llms/providers/together.py
llms/results/__init__.py
llms/results/result.py
pyllms-0.7.6.dist-info/licenses/LICENSE
tests/__init__.py
tests/conftest.py
tests/test_all_models.py
pyllms-0.7.6.dist-info/METADATA
pyllms-0.7.6.dist-info/WHEEL
pyllms-0.7.6.dist-info/top_level.txt
pyllms-0.7.6.dist-info/RECORD
