Metadata-Version: 2.4
Name: pyllms
Version: 0.7.6
Summary: Minimal Python library to connect to LLMs (OpenAI, Anthropic, Google, Mistral, OpenRouter, Reka, Groq, Together, Ollama, AI21, Cohere, Aleph-Alpha, HuggingfaceHub), with a built-in model performance benchmark.
Author: Vladimir Prelovac
Author-email: vlad@kagi.com
Project-URL: Documentation, https://github.com/kagisearch/pyllms
Project-URL: Source Code, https://github.com/kagisearch/pyllms
Project-URL: Issue Tracker, https://github.com/kagisearch/pyllms/issues
Keywords: llm,llms,large language model,AI,NLP,natural language processing,gpt,chatgpt,openai,anthropic,ai21,cohere,aleph alpha,huggingface hub,vertex ai,palm,palm2,deepseek
Classifier: Development Status :: 3 - Alpha
Classifier: Intended Audience :: Developers
Classifier: License :: OSI Approved :: MIT License
Classifier: Programming Language :: Python :: 3
Classifier: Programming Language :: Python :: 3.7
Classifier: Programming Language :: Python :: 3.8
Classifier: Programming Language :: Python :: 3.9
Classifier: Programming Language :: Python :: 3.10
Classifier: Programming Language :: Python :: 3.11
Classifier: Topic :: Scientific/Engineering :: Artificial Intelligence
Classifier: Topic :: Scientific/Engineering :: Human Machine Interfaces
Classifier: Topic :: Text Processing
Requires-Python: >=3.7
License-File: LICENSE
Requires-Dist: openai>=1
Requires-Dist: tiktoken
Requires-Dist: anthropic>=0.18
Requires-Dist: ai21
Requires-Dist: cohere
Requires-Dist: aleph-alpha-client
Requires-Dist: huggingface_hub
Requires-Dist: google-cloud-aiplatform
Requires-Dist: prettytable
Requires-Dist: protobuf>=3.20.3
Requires-Dist: grpcio>=1.54.2
Requires-Dist: google-generativeai
Requires-Dist: mistralai
Requires-Dist: ollama
Requires-Dist: reka-api
Requires-Dist: together
Provides-Extra: local
Requires-Dist: einops; extra == "local"
Requires-Dist: accelerate; extra == "local"
Dynamic: author
Dynamic: author-email
Dynamic: classifier
Dynamic: description
Dynamic: description-content-type
Dynamic: keywords
Dynamic: license-file
Dynamic: project-url
Dynamic: provides-extra
Dynamic: requires-dist
Dynamic: requires-python
Dynamic: summary
